LICENSE.txt
MANIFEST.in
README.rst
setup.cfg
setup.py
git_gdrive/__init__.py
git_gdrive/__main__.py
git_gdrive.egg-info/PKG-INFO
git_gdrive.egg-info/SOURCES.txt
git_gdrive.egg-info/dependency_links.txt
git_gdrive.egg-info/entry_points.txt
git_gdrive.egg-info/requires.txt
git_gdrive.egg-info/top_level.txt