Metadata-Version: 1.1
Name: git-gdrive
Version: 1.0.2
Summary: git-gdrive: format-patch / am over Google Drive
Home-page: https://github.com/primiano/git-gdrive
Author: Primiano Tucci
Author-email: p.tucci@gmail.com
License: BSD
Keywords: git development
Platform: UNKNOWN
Classifier: Development Status :: 5 - Production/Stable
Classifier: Intended Audience :: Developers
Classifier: Topic :: Software Development :: Build Tools
Classifier: License :: OSI Approved :: BSD License
Classifier: Programming Language :: Python :: 2
Classifier: Programming Language :: Python :: 2.6
Classifier: Programming Language :: Python :: 2.7
